whatenc/__init__.py
whatenc/api.py
whatenc/cli.py
whatenc-0.9.1.data/data/models/meta.json
whatenc-0.9.1.data/data/models/model.onnx
whatenc-0.9.1.data/data/models/model.onnx.data
whatenc-0.9.1.dist-info/licenses/LICENSE
whatenc-0.9.1.dist-info/METADATA
whatenc-0.9.1.dist-info/WHEEL
whatenc-0.9.1.dist-info/entry_points.txt
whatenc-0.9.1.dist-info/top_level.txt
whatenc-0.9.1.dist-info/RECORD
