Metadata-Version: 2.4
Name: whatenc
Version: 0.9.1
Summary: Text encoding type classifier
Project-URL: Homepage, https://github.com/jeremyctrl/whatenc
Project-URL: Repository, https://github.com/jeremyctrl/whatenc
Project-URL: Issues, https://github.com/jeremyctrl/whatenc/issues
Requires-Python: >=3.13
License-File: LICENSE
Requires-Dist: numpy>=2.3.4
Requires-Dist: onnxruntime>=1.23.2
Provides-Extra: dev
Requires-Dist: build>=1.3.0; extra == "dev"
Requires-Dist: twine>=6.2.0; extra == "dev"
Provides-Extra: train
Requires-Dist: datasets>=4.3.0; extra == "train"
Requires-Dist: onnxscript>=0.5.6; extra == "train"
Requires-Dist: requests>=2.32.5; extra == "train"
Requires-Dist: torch>=2.9.0; extra == "train"
Dynamic: license-file
